kubesurveyor/__init__.py
kubesurveyor/main.py
kubesurveyor-2.0.0.dist-info/METADATA
kubesurveyor-2.0.0.dist-info/WHEEL
kubesurveyor-2.0.0.dist-info/entry_points.txt
kubesurveyor-2.0.0.dist-info/RECORD
