Metadata-Version: 2.1
Name: kubesurveyor
Version: 2.0.0
Summary: Good enough Kubernetes namespace visualization tool
Home-page: https://github.com/viralpoetry/kubesurveyor
License: MIT
Keywords: kubernetes,graphviz,visualisation
Author: Peter Gasper
Author-email: peter@gasper.cc
Requires-Python: >=3.8,<4.0
Classifier: Intended Audience :: System Administrators
Classifier: License :: OSI Approved :: MIT License
Classifier: Operating System :: POSIX :: Linux
Classifier: Programming Language :: Python :: 3
Classifier: Programming Language :: Python :: 3.8
Classifier: Programming Language :: Python :: 3.9
Classifier: Programming Language :: Python :: 3.10
Classifier: Programming Language :: Python :: 3.11
Classifier: Programming Language :: Python :: 3.12
Classifier: Topic :: Scientific/Engineering :: Visualization
Requires-Dist: PyYAML (>=6.0.2,<7.0.0)
Requires-Dist: graphviz (>=0.20.3,<0.21.0)
Requires-Dist: kubernetes (>=30.1.0,<31.0.0)
Project-URL: Repository, https://github.com/viralpoetry/kubesurveyor
